py3repl/__init__.py
py3repl/pyrepl.py
py3repl-0.1.2.dist-info/entry_points.txt
py3repl-0.1.2.dist-info/WHEEL
py3repl-0.1.2.dist-info/METADATA
py3repl-0.1.2.dist-info/RECORD
