Metadata-Version: 2.1
Name: py3repl
Version: 0.1.2
Summary: A cli to mimic python REPL implementation
Home-page: https://github.com/amalshaji/pyrepl/
License: MIT
Keywords: python3,repl,Packages,Pip
Author: Amal Shaji
Author-email: amalshajid@gmail.com
Maintainer: Amal Shaji
Maintainer-email: amalshajid@gmail.com
Requires-Python: >=3.6,<4.0
Classifier: License :: OSI Approved :: MIT License
Classifier: Programming Language :: Python :: 3
Classifier: Programming Language :: Python :: 3.6
Classifier: Programming Language :: Python :: 3.7
Classifier: Programming Language :: Python :: 3.8
Classifier: Programming Language :: Python :: 3.9
Requires-Dist: colorama (>=0.4.3,<0.5.0)
Project-URL: Repository, https://github.com/amalshaji/pyrepl/
